slimschema/__init__.py
slimschema/backend.py
slimschema/coerce.py
slimschema/constraints.py
slimschema/errors.py
slimschema/formats.py
slimschema/schema.py
slimschema/slimschema_native.pyi
slimschema/spec.py
slimschema/validators.py
slimschema/adapters/__init__.py
slimschema/adapters/pydantic.py
slimschema-0.0.1.dev9.dist-info/METADATA
slimschema-0.0.1.dev9.dist-info/WHEEL
slimschema-0.0.1.dev9.dist-info/top_level.txt
slimschema-0.0.1.dev9.dist-info/RECORD
