Metadata-Version: 2.4
Name: slimschema
Version: 0.0.1.dev9
Summary: Token-efficient schema language for LLMs with fast Zig backend
Author: BotAssembly
License: MIT
Project-URL: Homepage, https://github.com/botassembly/slimschema
Project-URL: Repository, https://github.com/botassembly/slimschema
Classifier: Development Status :: 3 - Alpha
Classifier: Intended Audience :: Developers
Classifier: License :: OSI Approved :: MIT License
Classifier: Programming Language :: Python :: 3.10
Classifier: Programming Language :: Python :: 3.11
Classifier: Programming Language :: Python :: 3.12
Requires-Python: >=3.10
Requires-Dist: jsonschema>=4.20.0
Provides-Extra: pydantic
Requires-Dist: pydantic>=2.0.0; extra == "pydantic"
Provides-Extra: dev
Requires-Dist: pytest>=7.4.0; extra == "dev"
Requires-Dist: pytest-cov>=4.1.0; extra == "dev"
Requires-Dist: mktestdocs>=0.2; extra == "dev"
Requires-Dist: coverage>=7.0.0; extra == "dev"
Requires-Dist: mypy>=1.5.0; extra == "dev"
Requires-Dist: ruff>=0.1.0; extra == "dev"
Provides-Extra: all
Requires-Dist: slimschema[pydantic]; extra == "all"
